.coveragerc
.gitignore
AUTHORS.rst
CHANGELOG.rst
LICENSE.txt
README.md
pyproject.toml
setup.cfg
setup.py
tox.ini
docs/Makefile
docs/authors.rst
docs/changelog.rst
docs/conf.py
docs/index.rst
docs/license.rst
docs/_static/.gitignore
src/solidpython_ff/__init__.py
src/solidpython_ff.egg-info/PKG-INFO
src/solidpython_ff.egg-info/SOURCES.txt
src/solidpython_ff.egg-info/dependency_links.txt
src/solidpython_ff.egg-info/not-zip-safe
src/solidpython_ff.egg-info/requires.txt
src/solidpython_ff.egg-info/top_level.txt
tests/conftest.py