Metadata-Version: 2.1
Name: solidpython-ff
Version: 0.1.0
Summary: Solidpython - fast and furious extension
Home-page: https://github.com/TyberiusPrime/solidpython_ff
Author: Florian Finkernagel
Author-email: tyberius_prime@coonabibba.de
License: mit
Platform: any
Classifier: Development Status :: 4 - Beta
Classifier: Programming Language :: Python
Requires-Python: >=3.6
